ckanext_lapaz-0.0.11-py3.8-nspkg.pth
ckanext/lapaz/__init__.py
ckanext/lapaz/plugin.py
ckanext/lapaz/assets/webassets.yml
ckanext/lapaz/i18n/es/LC_MESSAGES/ckanext-lapaz.mo
ckanext/lapaz/public/MullerExtraBold.woff
ckanext/lapaz/public/MullerExtraBold.woff2
ckanext/lapaz/public/MullerLight.woff
ckanext/lapaz/public/MullerLight.woff2
ckanext/lapaz/public/MullerMedium.woff
ckanext/lapaz/public/MullerMedium.woff2
ckanext/lapaz/public/api.png
ckanext/lapaz/public/banner-background.png
ckanext/lapaz/public/download.png
ckanext/lapaz/public/example_theme.0.css
ckanext/lapaz/public/lapaz-logo.jpg
ckanext/lapaz/public/lapaz-logo.png
ckanext/lapaz/public/madrid.png
ckanext/lapaz/public/publish.png
ckanext/lapaz/public/redciudadana.png
ckanext/lapaz/public/ucci.jpg
ckanext/lapaz/public/ucci.png
ckanext/lapaz/public/ucci.svg
ckanext/lapaz/templates/base.html
ckanext/lapaz/templates/footer.html
ckanext/lapaz/templates/header.html
ckanext/lapaz/templates/page.html
ckanext/lapaz/templates/home/index.html
ckanext/lapaz/templates/home/layout1.html
ckanext/lapaz/templates/home/snippets/promoted.html
ckanext/lapaz/templates/home/snippets/search.html
ckanext/lapaz/tests/__init__.py
ckanext/lapaz/tests/test_plugin.py
ckanext_lapaz-0.0.11.dist-info/LICENSE
ckanext_lapaz-0.0.11.dist-info/METADATA
ckanext_lapaz-0.0.11.dist-info/WHEEL
ckanext_lapaz-0.0.11.dist-info/entry_points.txt
ckanext_lapaz-0.0.11.dist-info/namespace_packages.txt
ckanext_lapaz-0.0.11.dist-info/top_level.txt
ckanext_lapaz-0.0.11.dist-info/RECORD
