Metadata-Version: 2.1
Name: ckanext-lapaz
Version: 0.0.11
Summary: Theme for open data project in La Paz
Home-page: https://github.com/redciudadana/ckanext-lapaz
Author: Javier P.
Author-email: info@redciudadana.org.gt
License: AGPL
Keywords: CKAN la-paz open-data
Classifier: Development Status :: 4 - Beta
Classifier: License :: OSI Approved :: GNU Affero General Public License v3 or later (AGPLv3+)
Classifier: Programming Language :: Python :: 2.7
License-File: LICENSE
